omuplugin_obs/__init__.py
omuplugin_obs/__main__.py
omuplugin_obs/config.py
omuplugin_obs/const.py
omuplugin_obs/hwnd_helpers.py
omuplugin_obs/obsconfig.py
omuplugin_obs/permissions.py
omuplugin_obs/plugin.py
omuplugin_obs/types.py
omuplugin_obs/version.py
omuplugin_obs/obs/__init__.py
omuplugin_obs/obs/data.py
omuplugin_obs/obs/obs.py
omuplugin_obs/obs/property.py
omuplugin_obs/obs/reference.py
omuplugin_obs/obs/scene.py
omuplugin_obs/obs/source.py
omuplugin_obs/script/obsplugin.py
omuplugin_obs/script/omuapps_plugin.py
omuplugin_obs/script/venv_loader.py
omuplugin_obs-0.9.50.dist-info/METADATA
omuplugin_obs-0.9.50.dist-info/WHEEL
omuplugin_obs-0.9.50.dist-info/entry_points.txt
omuplugin_obs-0.9.50.dist-info/RECORD
