Metadata-Version: 2.4
Name: omuplugin_obs
Version: 0.9.50
Summary: OBS Studioの操作を行うためのOMUAPPSプラグイン
Author-email: am230 <111672334+am230@users.noreply.github.com>
Requires-Python: >=3.12
Requires-Dist: loguru>=0.7.2
Requires-Dist: omu-chat>=0.9.50
Requires-Dist: psutil>=6.0.0
Requires-Dist: pywin32>=306; sys_platform == 'win32'
